abstract_api/__init__.py
abstract_api/avatars/__init__.py
abstract_api/avatars/avatars.py
abstract_api/avatars/avatars_response.py
abstract_api/company_enrichment/__init__.py
abstract_api/company_enrichment/_response_fields.py
abstract_api/company_enrichment/company_enrichment.py
abstract_api/company_enrichment/company_enrichment_response.py
abstract_api/core/__init__.py
abstract_api/core/bases/__init__.py
abstract_api/core/bases/_base_response.py
abstract_api/core/bases/base_service.py
abstract_api/core/bases/file_response.py
abstract_api/core/bases/json_response.py
abstract_api/core/common_entities/__init__.py
abstract_api/core/common_entities/country.py
abstract_api/core/exceptions/__init__.py
abstract_api/core/exceptions/abstract_api_exception.py
abstract_api/core/exceptions/api_request_error.py
abstract_api/core/exceptions/client_request_error.py
abstract_api/core/exceptions/response_parse_error.py
abstract_api/core/mixins/__init__.py
abstract_api/core/mixins/nested_entities_mixin.py
abstract_api/core/mixins/response_fields_mixin.py
abstract_api/core/validators/__init__.py
abstract_api/core/validators/numerical.py
abstract_api/email_validation/__init__.py
abstract_api/email_validation/_response_fields.py
abstract_api/email_validation/email_validation.py
abstract_api/email_validation/email_validation_response.py
abstract_api/exchange_rates/__init__.py
abstract_api/exchange_rates/_multiple_exchange_rates_response.py
abstract_api/exchange_rates/exchange_rates.py
abstract_api/exchange_rates/exchange_rates_conversion_response.py
abstract_api/exchange_rates/historical_exchange_rates_response.py
abstract_api/exchange_rates/live_exchange_rates_response.py
abstract_api/exchange_rates/_response_fields/__init__.py
abstract_api/exchange_rates/_response_fields/conversion.py
abstract_api/exchange_rates/_response_fields/historical.py
abstract_api/exchange_rates/_response_fields/live.py
abstract_api/holidays/__init__.py
abstract_api/holidays/_response_fields.py
abstract_api-1.0.0.dist-info/LICENSE
abstract_api-1.0.0.dist-info/METADATA
abstract_api-1.0.0.dist-info/WHEEL
abstract_api-1.0.0.dist-info/top_level.txt
abstract_api-1.0.0.dist-info/RECORD
