Metadata-Version: 2.1
Name: abstract-api
Version: 1.0.0
Summary: Python SDK for using AbstractAPI services
Author-email: Ebram Shehata <ebram96@gmail.com>
Maintainer-email: Ebram Shehata <ebram96@gmail.com>
License: MIT License
Project-URL: Homepage, https://github.com/ebram96/AbstractAPI-Python-SDK
Project-URL: Bug Tracker, https://github.com/ebram96/AbstractAPI-Python-SDK/issues
Project-URL: Repository, https://github.com/ebram96/AbstractAPI-Python-SDK.git
Keywords: sdk,abstract,api,abstract api
Classifier: Programming Language :: Python :: 3
Classifier: Programming Language :: Python :: 3 :: Only
Classifier: Programming Language :: Python :: 3.9
Classifier: Programming Language :: Python :: 3.10
Classifier: Programming Language :: Python :: 3.11
Classifier: Programming Language :: Python :: 3.12
Classifier: License :: OSI Approved :: MIT License
Classifier: Operating System :: OS Independent
Classifier: Intended Audience :: Developers
Requires-Python: >=3.9
License-File: LICENSE
Requires-Dist: requests >=2.31.0
